{"id": "aht1719471196112", "title": "stmtcache", "breadcrumbs": ["DBMS Support", "Database Connectors", "Microsoft SQL Server", "MSS Connector Options", "stmtcache"], "url": "https://docs.rocketsoftware.com/de-DE/bundle/uniface_104/page/aht1719471196112.html", "text": "stmtcache Specify whether Uniface should enable or disable the Uniface cache mechanism for statements. USYS$Mnemonic_PARAMS = stmtcache : on | off Values off —Uniface statement cache is disabled. Note: This may reduce performance to some degree. on —Uniface statement cache is enabled. Default. Note: When stmtcache is set to on , the number of statements that can be cached is only limited by the system memory. Use Applies to Mnemonic Connector Syntax Microsoft SQL connector MSS USYS$MSS_PARAMS PostgreSQL connector PGS USYS$PGS_PARAMS stmtcache The following example specifies that the DBMS is responsible for maintaining referential integrity, that the connector will not use stored procedures, and that Uniface statement cache is disabled: USYS$MSS_PARAMS ri:dbms, procs:off, stmtcache:off Copy Was this topic helpful? Like Dislike"}