{"id": "piw1665703556047", "title": "JavaScript Object Notation (JSON)", "breadcrumbs": ["Uniface Glossary", "Glossary: J", "JavaScript Object Notation (JSON)"], "url": "https://docs.rocketsoftware.com/de-DE/bundle/uniface_104/page/piw1665703556047.html", "text": "JavaScript Object Notation (JSON) JavaScript Object Notation. A lightweight data-interchange format based on a subset of JavaScript. It is a text format that is language independent, easy for humans to read and write, and for machines to parse and generate. Was this topic helpful? Like Dislike"}