{"id": "rnt1665703107711", "title": "Columns (cols)", "breadcrumbs": ["Uniface Reference", "Development Object and Property Reference", "Development Object Properties", "Presentation Properties", "USP Widget Properties", "Control Properties", "Columns (cols)"], "url": "https://docs.rocketsoftware.com/de-DE/bundle/uniface_104/page/rnt1665703107711.html", "text": "Columns (cols) Widget property that specifies the width of a text area in a static server page in number of characters. cols = Number Usage Dynamic? No Supported in Grid? No Dependencies: None Applies To TextArea Was this topic helpful? Like Dislike"}