{"id": "rwc1665702825920", "title": "Compiler Output", "breadcrumbs": ["Uniface IDE", "Uniface IDE Editors", "Output Tabs", "Compiler Output"], "url": "https://docs.rocketsoftware.com/de-DE/bundle/uniface_104/page/rwc1665702825920.html", "text": "Compiler Output The Compiler Output tab displays the results of the compilation process, including warning and error messages, if they occur. Compilation is started when you click the Compile or Compile & Test command. Will it be possible to configure the Compiler Output tab? For example, the number of lines that can be displayed, or displaying warning and info messages as well as error messages? Configuring the Compile Output tab Clearing the Compile Output tab Related Links Compilation When Uniface development objects are compiled, the compiler checks the definition, syntax, and integrity of the object, inserts inherited ProcScript modules, resolves IncludeScript references and constant definitions, compiles the resulting code, and generates compiled runtime objects and descriptors. It can optionally generate files that show an object's ProcScript after inherited and included ProcScript has been resolved. Was this topic helpful? Like Dislike"}