{"id": "thj1665702664733", "title": "Data Retrieval on SEQ", "breadcrumbs": ["DBMS Support", "Database Connectors", "Sequential", "Data Retrieval on SEQ"], "url": "https://docs.rocketsoftware.com/de-DE/bundle/uniface_104/page/thj1665702664733.html", "text": "Data Retrieval on SEQ When opening sequential files, Uniface attempts to establish both read and write access. If this fails, Uniface opens them with read-only access. Users can read data, but any attempt to update the data causes the appropriate warning or error message to be returned. Because SEQ is based on system-dependent I/O calls, it is not possible for the connector to distinguish between violation of read-only access and any other I/O error. If users have read-only access and they try to write to a sequential file, inappropriate messages can result, including bad file number , or occurrence no longer exists . Remember that there is no locking available at any time; sequential files should be used by single users only. You should take these limitations into account when using the SEQ connector in a production environment. The retrieveSequential trigger is not supported. Related Links Data Retrieval Every DBMS connector recognizes the same set of connector I/O requests. When retrieving data from the database, Uniface selects the required data with the Select connector request, and fetches it into the component with the Fetch connector request. Uniface uses the Select request to create a partially built hitlist called a stepped hitlist. Data Retrieval Support In response to read and selectdb ProcScript instructions, Uniface issues connector requests to select data into a hitlist and fetch it into the calling component. Special considerations and restrictions may apply for some databases. Was this topic helpful? Like Dislike"}