{"id": "wtz1701568362724", "title": "unblockUI", "breadcrumbs": ["Uniface Reference", "API Reference", "APIs: DSP UX Widget Class", "unblockUI"], "url": "https://docs.rocketsoftware.com/de-DE/bundle/uniface_104/page/wtz1701568362724.html", "text": "unblockUI Enables user interaction for the current widget. unblockUI() Arguments None Exceptions None Return value None Description The framework calls the unblockUI() function to inform the widget to enable user interaction. It is called when the DSP framework completes the execution of asynchronous processes for which it was blocked. Was this topic helpful? Like Dislike"}