{"id": "wzk1665702797572", "title": "Formats Library", "breadcrumbs": ["Uniface IDE", "Uniface IDE Editors", "More Editors", "Library", "Formats Library"], "url": "https://docs.rocketsoftware.com/de-DE/bundle/uniface_104/page/wzk1665702797572.html", "text": "Formats Library Use this editor to define formats for drag and drop functionality. Drag and drop formats define drag and drop behavior, including the default action, pop-up menu, and icon available when performing drag and drop actions in specific widgets. The name of the format must be unique within the library and language definition, but it can be the same as a format in another library. Properties Name Language Description Default Action Option Text Mouse Pointer Icon Comments How to Create and Maintain Drag-and-Drop Formats Related Links Drag and Drop Behavior Drag and drop behavior enables the user to select an object and drag it to another location with the mouse. When the mouse button is released, the selected object is copied, moved, or linked to by a shortcut. Drag-and-Drop Formats Drag-and-drop formats are global objects that define drag and drop behavior, including the default action, pop-up menu, and icon that are available when performing drag and drop actions in the tree and picture widgets. They are not used for drag-and-drop widgets. Was this topic helpful? Like Dislike"}